README.md
setup.cfg
setup.py
likert_plot/__init__.py
likert_plot/likert_plot.py
pylikert_plot.egg-info/PKG-INFO
pylikert_plot.egg-info/SOURCES.txt
pylikert_plot.egg-info/dependency_links.txt
pylikert_plot.egg-info/requires.txt
pylikert_plot.egg-info/top_level.txt