Metadata-Version: 1.1
Name: pylikert-plot
Version: 0.0.1
Summary: Plot likert questions in stacked distributed plot style
Home-page: https://github.com/jennnifer90/pylikert-plot
Author: Cong Wang
Author-email: UNKNOWN
License: MIT
Keywords: likert,matplotlib,survey
Platform: UNKNOWN
Classifier: Development Status :: 3 - Alpha
Classifier: Intended Audience :: Developers
Classifier: Topic :: Software Development :: Build Tools
Classifier: License :: OSI Approved :: MIT License
Classifier: Programming Language :: Python :: 3
